synthcal/__init__.py
synthcal/__main__.py
synthcal/api.py
synthcal/cli.py
synthcal/util.py
synthcal/camera/__init__.py
synthcal/camera/model.py
synthcal/core/__init__.py
synthcal/core/geometry.py
synthcal/core/seeding.py
synthcal/effects/__init__.py
synthcal/effects/config.py
synthcal/effects/pipeline.py
synthcal/io/__init__.py
synthcal/io/config.py
synthcal/io/generate.py
synthcal/io/manifest.py
synthcal/laser/__init__.py
synthcal/laser/centerline.py
synthcal/laser/intersection.py
synthcal/laser/model.py
synthcal/render/__init__.py
synthcal/render/chessboard.py
synthcal/render/gt.py
synthcal/render/stripe.py
synthcal/scenario/__init__.py
synthcal/scenario/config.py
synthcal/scenario/constraints.py
synthcal/scenario/sampling.py
synthcal/targets/__init__.py
synthcal/targets/chessboard.py
synthcal-0.1.0.dist-info/METADATA
synthcal-0.1.0.dist-info/WHEEL
synthcal-0.1.0.dist-info/entry_points.txt
synthcal-0.1.0.dist-info/licenses/LICENSE
synthcal-0.1.0.dist-info/RECORD
