Metadata-Version: 2.4
Name: synthcal
Version: 0.1.0
Summary: Synthetic dataset generator for camera + laser-stripe calibration.
Author: synthcal contributors
License: MIT License
License-File: LICENSE
Classifier: Development Status :: 3 - Alpha
Classifier: Intended Audience :: Science/Research
Classifier: License :: OSI Approved :: MIT License
Classifier: Programming Language :: Python :: 3
Classifier: Programming Language :: Python :: 3 :: Only
Classifier: Programming Language :: Python :: 3.10
Classifier: Programming Language :: Python :: 3.11
Classifier: Programming Language :: Python :: 3.12
Classifier: Topic :: Scientific/Engineering
Requires-Python: >=3.10
Requires-Dist: matplotlib>=3.7
Requires-Dist: numpy>=1.23
Requires-Dist: pillow>=10.0
Requires-Dist: pyyaml>=6.0
Provides-Extra: dev
Requires-Dist: build>=1.0; extra == 'dev'
Requires-Dist: pytest>=7.4; extra == 'dev'
Requires-Dist: ruff>=0.5; extra == 'dev'
Requires-Dist: twine>=5.0; extra == 'dev'
Provides-Extra: scipy
Requires-Dist: scipy>=1.10; extra == 'scipy'
